Workbook

Sheet Resumen
A1: RUMOTECH CONNECT — Modelo de Comercialización NexoLibre
A2: Tarifa variable por estudio, SEGMENTADA POR PAÍS · Chile · Uruguay · Argentina · Colombia · USA
A3: Confidencial · 13 de julio de 2026 · Modelo vivo — editar inputs en 'Supuestos'
A5: LA IDEA EN UNA LÍNEA
A6: Rumotech traslada a NexoLibre un costo FIJO por modalidad (USD, igual en todos los países). NexoLibre revende como precio VARIABLE por estudio, ajustado al valor del estudio en cada mercado. El spread neto de impuestos es la renta pasiva por servicio.
A9: PALANCAS Y RESULTADOS CLAVE
A10: Costo fijo Rumotech / modalidad / mes (USD, fijo global) | E10: =Supuestos!$B$5
A11: Precio SaaS / estudio — USA (mercado más caro) | E11: =Supuestos!$E$15
A12: Precio SaaS / estudio — Argentina (mercado más barato) | E12: =Supuestos!$E$13
A13: Renta neta anual / modalidad — Medio (prom. países) | E13: =AVERAGE('Renta Anual'!C5:C9)
A14: Break-even Argentina (estudios/mes) | E14: =Supuestos!$B$5/Supuestos!$E$13
A15: Break-even USA (estudios/mes) | E15: =Supuestos!$B$5/Supuestos!$E$15
A17: RECOMENDACIÓN
A18: Precio segmentado por país anclado a ~0,5–0,6% del valor del estudio local: USA 2,00 · Chile 1,20 · Uruguay 1,00 · Colombia 0,60 · Argentina 0,40 (neto de IVA). Como el costo de Rumotech es fijo en USD, en mercados baratos el precio no puede caer más sin licuar el margen: allí el punto de equilibrio en volumen sube (Argentina ~250 est./mes) y el piso mensual protege la renta. Para escalar en Argentina/Colombia conviene, además, negociar con Rumotech un costo fijo menor.
A24: Hojas: Supuestos · Modelo por Estudio · Renta Anual · Precios por País

Sheet Supuestos
A1: RUMOTECH CONNECT · Modelo de Comercialización NexoLibre — Supuestos e Inputs
A2: AZUL = inputs editables · AMARILLO = palanca clave · Todo lo demás se recalcula.
A4: 1 · COSTO (Rumotech → NexoLibre) — FIJO en USD, igual para todos los países
A5: Costo fijo por modalidad por mes (USD) | B5: 100
A6: Costo fijo por modalidad por año (USD) | B6: =Supuestos!$B$5*12
A8: 2 · PRECIO POR ESTUDIO SEGMENTADO POR PAÍS
A9: Metodología: el precio del SaaS por estudio se ancla a un % pequeño del valor de un estudio (RM) en cada país. En mercados baratos/volátiles el precio baja, pero NO por debajo del piso que impone el costo fijo de Rumotech.
A10: País | B10: IVA / consumo | C10: Imp. a la renta | D10: Valor ref. estudio RM (USD) | E10: Precio SaaS /estudio (USD) | F10: Take-rate (% del estudio) | G10: IIBB % (Arg.)
A11: Chile | B11: 0.19 | C11: 0.27 | D11: 200 | E11: 1.2 | F11: =IF(D11=0,0,E11/D11) | G11: 0
A12: Uruguay | B12: 0.22 | C12: 0.25 | D12: 180 | E12: 1 | F12: =IF(D12=0,0,E12/D12) | G12: 0
A13: Argentina | B13: 0.21 | C13: 0.35 | D13: 80 | E13: 0.4 | F13: =IF(D13=0,0,E13/D13) | G13: 0.03
A14: Colombia | B14: 0.19 | C14: 0.35 | D14: 120 | E14: 0.6 | F14: =IF(D14=0,0,E14/D14) | G14: 0
A15: USA | B15: 0 | C15: 0.21 | D15: 400 | E15: 2 | F15: =IF(D15=0,0,E15/D15) | G15: 0
A17: 3 · ESCENARIOS DE VOLUMEN (estudios/mes por modalidad)
A18: Bajo | B18: 250
A19: Medio | B19: 500
A20: Alto | B20: 900
A22: 4 · SALVAGUARDA
A23: Piso mensual por modalidad (mínimo facturable, USD) | B23: 200

Sheet Calculadora
A1: Calculadora de Escenarios — Rentabilidad por Cliente
A2: El costo de Rumotech es por MODALIDAD y por SEDE (no por equipo), salvo RM con EBOX (por resonador). Editá las celdas AZULES. Los comentarios (triángulo rojo) explican cada valor.
A4: CONFIGURACIÓN DEL CLIENTE
A5: País (elegí de la lista) | B5: Argentina
A6: Número de sedes | B6: 5
A7: Plan para RM | B7: SaaS Full + Cryogenics
A8: EBOX Full — costo anual por resonador (USD) | B8: 10000
A9: Método de volumen | B9: Por equipos
A10: Pacientes / mes por sede | B10: 900
A11: Coeficiente de exámenes por paciente | B11: 1.3
A13: Modalidad | B13: Equipos por sede | C13: Estudios / equipo / mes | D13: Modalidad activa | E13: Costo Rumotech / sede (USD) | F13: Volumen / sede (equipos)
A14: Resonancia (RM) | B14: 1 | C14: 500 | D14: =IF(B14>0,1,0) | E14: =IF(B14>0,IF($B$7="EBOX Full",($B$8/12)*B14,Supuestos!$B$5),0) | F14: =B14*C14
A15: Tomografía (CT) | B15: 1 | C15: 700 | D15: =IF(B15>0,1,0) | E15: =IF(B15>0,IF($B$7="EBOX Full",2100/12,Supuestos!$B$5),0) | F15: =B15*C15
A16: Ultrasonido (US) | B16: 0 | C16: 1000 | D16: =IF(B16>0,1,0) | E16: =IF(B16>0,IF($B$7="EBOX Full",2100/12,Supuestos!$B$5),0) | F16: =B16*C16
A17: Rayos X (RX) | B17: 0 | C17: 1200 | D17: =IF(B17>0,1,0) | E17: =IF(B17>0,IF($B$7="EBOX Full",2100/12,Supuestos!$B$5),0) | F17: =B17*C17
A18: Mamografía (MG) | B18: 0 | C18: 300 | D18: =IF(B18>0,1,0) | E18: =IF(B18>0,IF($B$7="EBOX Full",2100/12,Supuestos!$B$5),0) | F18: =B18*C18
A19: Total por sede | D19: =SUM(D14:D18) | E19: =SUM(E14:E18) | F19: =SUM(F14:F18)
A21: RESULTADOS DEL CLIENTE (todas las sedes)
A22: 1 · PRECIOS DE VENTA
A23: Precio de venta por prestación (sin IVA) | E23: =INDEX(Supuestos!$E$11:$E$15,MATCH($B$5,Supuestos!$A$11:$A$15,0))
A24: IVA por prestación | E24: =E23*INDEX(Supuestos!$B$11:$B$15,MATCH($B$5,Supuestos!$A$11:$A$15,0))
A25: Precio facturado por prestación (c/IVA) | E25: =E23+E24
A26: 2 · INGRESOS
A27: Prestaciones por sede / mes | E27: =IF($B$9="Por pacientes",$B$10*$B$11,F19)
A28: Volumen total de prestaciones / mes | E28: =E27*$B$6
A29: Ingreso BRUTO / mes (sin IVA) | E29: =E28*E23
A30: Facturación total / mes (c/IVA) | E30: =E29*(1+INDEX(Supuestos!$B$11:$B$15,MATCH($B$5,Supuestos!$A$11:$A$15,0)))
A31: 3 · COSTOS (fijos — según la propuesta Rumotech adjunta)
A32: Costo Rumotech / mes — total | E32: =E19*$B$6
A33: Costo efectivo por prestación | E33: =IF(E28=0,0,E32/E28)
A34: Hardware (pago ÚNICO) | E34: =IF($B$7="EBOX Full",500,150)*B14*$B$6
A35: 4 · IMPUESTOS
A36: IVA trasladado / mes | E36: =E29*INDEX(Supuestos!$B$11:$B$15,MATCH($B$5,Supuestos!$A$11:$A$15,0))
A37: Ingresos Brutos (IIBB) / mes | E37: =E30*INDEX(Supuestos!$G$11:$G$15,MATCH($B$5,Supuestos!$A$11:$A$15,0))
A38: Impuesto a las ganancias / mes | E38: =IF(E40>0,E40*INDEX(Supuestos!$C$11:$C$15,MATCH($B$5,Supuestos!$A$11:$A$15,0)),0)
A39: 5 · RESULTADO
A40: Margen bruto / mes | E40: =E29-E32
A41: GANANCIA NETA / mes | E41: =E40-E37-E38
A42: GANANCIA NETA ANUAL — total cliente | E42: =E41*12
A44: Cada etiqueta tiene un comentario (triángulo rojo) que explica el dato y su fórmula. Ejercicios: cambiá el plan de RM, el método de volumen o el país.

Sheet Modelo por Estudio
A1: Economía por Estudio — Renta Pasiva Neta por Servicio (precio segmentado por país)
A2: Costo unitario Rumotech = costo mensual ÷ volumen. Renta neta = margen bruto × (1 − imp. renta). IVA pass-through (neutro).
A4: País | B4: Escenario | C4: Volumen (est./mes) | D4: Costo Rumotech /estudio | E4: Precio SaaS /estudio | F4: Margen bruto /estudio | G4: Margen % | H4: Imp. renta | I4: Renta neta /estudio | J4: Renta neta mensual | K4: Renta neta anual
A5: Chile | B5: Bajo | C5: =Supuestos!$B$18 | D5: =Supuestos!$B$5/C5 | E5: =Supuestos!$E$11 | F5: =E5-D5 | G5: =IF(E5=0,0,F5/E5) | H5: =Supuestos!$C$11 | I5: =F5*(1-H5) | J5: =I5*C5 | K5: =J5*12
A6: Chile | B6: Medio | C6: =Supuestos!$B$19 | D6: =Supuestos!$B$5/C6 | E6: =Supuestos!$E$11 | F6: =E6-D6 | G6: =IF(E6=0,0,F6/E6) | H6: =Supuestos!$C$11 | I6: =F6*(1-H6) | J6: =I6*C6 | K6: =J6*12
A7: Chile | B7: Alto | C7: =Supuestos!$B$20 | D7: =Supuestos!$B$5/C7 | E7: =Supuestos!$E$11 | F7: =E7-D7 | G7: =IF(E7=0,0,F7/E7) | H7: =Supuestos!$C$11 | I7: =F7*(1-H7) | J7: =I7*C7 | K7: =J7*12
A8: Uruguay | B8: Bajo | C8: =Supuestos!$B$18 | D8: =Supuestos!$B$5/C8 | E8: =Supuestos!$E$12 | F8: =E8-D8 | G8: =IF(E8=0,0,F8/E8) | H8: =Supuestos!$C$12 | I8: =F8*(1-H8) | J8: =I8*C8 | K8: =J8*12
A9: Uruguay | B9: Medio | C9: =Supuestos!$B$19 | D9: =Supuestos!$B$5/C9 | E9: =Supuestos!$E$12 | F9: =E9-D9 | G9: =IF(E9=0,0,F9/E9) | H9: =Supuestos!$C$12 | I9: =F9*(1-H9) | J9: =I9*C9 | K9: =J9*12
A10: Uruguay | B10: Alto | C10: =Supuestos!$B$20 | D10: =Supuestos!$B$5/C10 | E10: =Supuestos!$E$12 | F10: =E10-D10 | G10: =IF(E10=0,0,F10/E10) | H10: =Supuestos!$C$12 | I10: =F10*(1-H10) | J10: =I10*C10 | K10: =J10*12
A11: Argentina | B11: Bajo | C11: =Supuestos!$B$18 | D11: =Supuestos!$B$5/C11 | E11: =Supuestos!$E$13 | F11: =E11-D11 | G11: =IF(E11=0,0,F11/E11) | H11: =Supuestos!$C$13 | I11: =F11*(1-H11) | J11: =I11*C11 | K11: =J11*12
A12: Argentina | B12: Medio | C12: =Supuestos!$B$19 | D12: =Supuestos!$B$5/C12 | E12: =Supuestos!$E$13 | F12: =E12-D12 | G12: =IF(E12=0,0,F12/E12) | H12: =Supuestos!$C$13 | I12: =F12*(1-H12) | J12: =I12*C12 | K12: =J12*12
A13: Argentina | B13: Alto | C13: =Supuestos!$B$20 | D13: =Supuestos!$B$5/C13 | E13: =Supuestos!$E$13 | F13: =E13-D13 | G13: =IF(E13=0,0,F13/E13) | H13: =Supuestos!$C$13 | I13: =F13*(1-H13) | J13: =I13*C13 | K13: =J13*12
A14: Colombia | B14: Bajo | C14: =Supuestos!$B$18 | D14: =Supuestos!$B$5/C14 | E14: =Supuestos!$E$14 | F14: =E14-D14 | G14: =IF(E14=0,0,F14/E14) | H14: =Supuestos!$C$14 | I14: =F14*(1-H14) | J14: =I14*C14 | K14: =J14*12
A15: Colombia | B15: Medio | C15: =Supuestos!$B$19 | D15: =Supuestos!$B$5/C15 | E15: =Supuestos!$E$14 | F15: =E15-D15 | G15: =IF(E15=0,0,F15/E15) | H15: =Supuestos!$C$14 | I15: =F15*(1-H15) | J15: =I15*C15 | K15: =J15*12
A16: Colombia | B16: Alto | C16: =Supuestos!$B$20 | D16: =Supuestos!$B$5/C16 | E16: =Supuestos!$E$14 | F16: =E16-D16 | G16: =IF(E16=0,0,F16/E16) | H16: =Supuestos!$C$14 | I16: =F16*(1-H16) | J16: =I16*C16 | K16: =J16*12
A17: USA | B17: Bajo | C17: =Supuestos!$B$18 | D17: =Supuestos!$B$5/C17 | E17: =Supuestos!$E$15 | F17: =E17-D17 | G17: =IF(E17=0,0,F17/E17) | H17: =Supuestos!$C$15 | I17: =F17*(1-H17) | J17: =I17*C17 | K17: =J17*12
A18: USA | B18: Medio | C18: =Supuestos!$B$19 | D18: =Supuestos!$B$5/C18 | E18: =Supuestos!$E$15 | F18: =E18-D18 | G18: =IF(E18=0,0,F18/E18) | H18: =Supuestos!$C$15 | I18: =F18*(1-H18) | J18: =I18*C18 | K18: =J18*12
A19: USA | B19: Alto | C19: =Supuestos!$B$20 | D19: =Supuestos!$B$5/C19 | E19: =Supuestos!$E$15 | F19: =E19-D19 | G19: =IF(E19=0,0,F19/E19) | H19: =Supuestos!$C$15 | I19: =F19*(1-H19) | J19: =I19*C19 | K19: =J19*12
A21: Fila sombreada = escenario base (Medio). Precios y volúmenes se editan en 'Supuestos'.

Sheet Renta Anual
A1: Renta Pasiva Neta Anual por Modalidad y Punto de Equilibrio, por País (USD)
A2: Break-even = estudios/mes para cubrir el costo fijo de Rumotech. En mercados baratos sube y el piso mensual se vuelve clave.
A4: País | B4: Renta anual Bajo | C4: Renta anual Medio | D4: Renta anual Alto | E4: Break-even (est./mes) | F4: Take-rate
A5: Chile | B5: ='Modelo por Estudio'!K5 | C5: ='Modelo por Estudio'!K6 | D5: ='Modelo por Estudio'!K7 | E5: =Supuestos!$B$5/Supuestos!$E$11 | F5: =Supuestos!$F$11
A6: Uruguay | B6: ='Modelo por Estudio'!K8 | C6: ='Modelo por Estudio'!K9 | D6: ='Modelo por Estudio'!K10 | E6: =Supuestos!$B$5/Supuestos!$E$12 | F6: =Supuestos!$F$12
A7: Argentina | B7: ='Modelo por Estudio'!K11 | C7: ='Modelo por Estudio'!K12 | D7: ='Modelo por Estudio'!K13 | E7: =Supuestos!$B$5/Supuestos!$E$13 | F7: =Supuestos!$F$13
A8: Colombia | B8: ='Modelo por Estudio'!K14 | C8: ='Modelo por Estudio'!K15 | D8: ='Modelo por Estudio'!K16 | E8: =Supuestos!$B$5/Supuestos!$E$14 | F8: =Supuestos!$F$14
A9: USA | B9: ='Modelo por Estudio'!K17 | C9: ='Modelo por Estudio'!K18 | D9: ='Modelo por Estudio'!K19 | E9: =Supuestos!$B$5/Supuestos!$E$15 | F9: =Supuestos!$F$15
A10: Promedio | B10: =AVERAGE(B5:B9) | C10: =AVERAGE(C5:C9) | D10: =AVERAGE(D5:D9)

Sheet Precios por País
A1: Comparativo de Precios por País — escenario base (500 estudios/mes)
A2: Muestra cómo el precio segmentado sostiene la renta en mercados caros y por qué el costo fijo aprieta el margen en los baratos.
A4: País | B4: Valor ref. estudio (USD) | C4: Precio SaaS /estudio (USD) | D4: Take-rate | E4: Break-even (est./mes) | F4: Renta neta /estudio (Medio) | G4: Renta neta anual (Medio)
A5: Chile | B5: =Supuestos!$D$11 | C5: =Supuestos!$E$11 | D5: =Supuestos!$F$11 | E5: =Supuestos!$B$5/Supuestos!$E$11 | F5: ='Modelo por Estudio'!I6 | G5: ='Modelo por Estudio'!K6
A6: Uruguay | B6: =Supuestos!$D$12 | C6: =Supuestos!$E$12 | D6: =Supuestos!$F$12 | E6: =Supuestos!$B$5/Supuestos!$E$12 | F6: ='Modelo por Estudio'!I9 | G6: ='Modelo por Estudio'!K9
A7: Argentina | B7: =Supuestos!$D$13 | C7: =Supuestos!$E$13 | D7: =Supuestos!$F$13 | E7: =Supuestos!$B$5/Supuestos!$E$13 | F7: ='Modelo por Estudio'!I12 | G7: ='Modelo por Estudio'!K12
A8: Colombia | B8: =Supuestos!$D$14 | C8: =Supuestos!$E$14 | D8: =Supuestos!$F$14 | E8: =Supuestos!$B$5/Supuestos!$E$14 | F8: ='Modelo por Estudio'!I15 | G8: ='Modelo por Estudio'!K15
A9: USA | B9: =Supuestos!$D$15 | C9: =Supuestos!$E$15 | D9: =Supuestos!$F$15 | E9: =Supuestos!$B$5/Supuestos!$E$15 | F9: ='Modelo por Estudio'!I18 | G9: ='Modelo por Estudio'!K18
A11: Argentina resaltado: precio bajo → break-even alto y renta fina. El piso mensual y/o renegociar el costo fijo de Rumotech son las palancas para ese mercado.
